LICENSE
README.md
setup.py
rrcf/__init__.py
rrcf/rrcf.py
rrcf/shingle.py
rrcf.egg-info/PKG-INFO
rrcf.egg-info/SOURCES.txt
rrcf.egg-info/dependency_links.txt
rrcf.egg-info/requires.txt
rrcf.egg-info/top_level.txt
test/test_rrcf.py