Metadata-Version: 2.1
Name: rrcf
Version: 0.4.4
Summary: Robust random cut forest for anomaly detection
Home-page: http://open-storm.org
Author: Matt Bartos, Abhiram Mullapudi, Sara Troutman
Author-email: mdbartos@umich.edu, abhiramm@umich.edu, stroutm@umich.edu
License: MIT
Platform: UNKNOWN
License-File: LICENSE
